molbery/__init__.py
molbery/__main__.py
molbery/molbery.py
molbery-1.0.6.dist-info/DESCRIPTION.rst
molbery-1.0.6.dist-info/METADATA
molbery-1.0.6.dist-info/RECORD
molbery-1.0.6.dist-info/WHEEL
molbery-1.0.6.dist-info/entry_points.txt
molbery-1.0.6.dist-info/metadata.json
molbery-1.0.6.dist-info/top_level.txt
