Metadata-Version: 2.0
Name: molbery
Version: 1.0.6
Summary: A tool for Molecular biologists to design modified Molecular Beacons which works on Exonuclease III Aided Target Recycling strategy for the detection of nucleic acid signatures.
Home-page: https://github.com/bhagya-ct/molbery
Author: Manu S
Author-email: manuvaivasvata7@gmail.com
License: UNKNOWN
Keywords: molecular beacons,EATR,CEAM,EXOIII,Target recycling
Platform: UNKNOWN
Classifier: Development Status :: 5 - Production/Stable
Classifier: Intended Audience :: Science/Research
Classifier: Natural Language :: English
Classifier: Topic :: Utilities
Classifier: License :: OSI Approved :: MIT License
Classifier: Programming Language :: Python :: 2.7
Classifier: Programming Language :: Python :: 3.5
Classifier: Topic :: Scientific/Engineering :: Bio-Informatics
Classifier: Operating System :: Microsoft :: Windows
Classifier: Operating System :: POSIX :: Linux
Requires-Dist: argparse
Requires-Dist: biopython
Requires-Dist: joblib
Requires-Dist: regex
Requires-Dist: tabulate
